crazyKhoreia/_3DIoU.py
crazyKhoreia/__init__.py
crazyKhoreia/crazyKhoreia.py
crazyKhoreia/lightPainting.py
crazyKhoreia/multiDroneFormation.py
crazyKhoreia-0.0.4.dist-info/LICENSE
crazyKhoreia-0.0.4.dist-info/METADATA
crazyKhoreia-0.0.4.dist-info/WHEEL
crazyKhoreia-0.0.4.dist-info/top_level.txt
crazyKhoreia-0.0.4.dist-info/RECORD
