Metadata-Version: 2.1
Name: crazyKhoreia
Version: 0.0.4
Summary: Python package for the crazyKhoreia project.
Home-page: https://github.com/santiagorg2401/crazyKhoreia
Author: Santiago Restrepo Garcia
Author-email: sanrega24@gmail.com
Project-URL: Bug Tracker, https://github.com/santiagorg2401/crazyKhoreia/issues
Classifier: Development Status :: 3 - Alpha
Classifier: Programming Language :: Python :: 3
Classifier: License :: OSI Approved :: GNU Affero General Public License v3
Classifier: Operating System :: OS Independent
Requires-Python: >=3.6
License-File: LICENSE
Requires-Dist: cycler
Requires-Dist: matplotlib
Requires-Dist: numpy
Requires-Dist: opencv-python
Requires-Dist: scikit-learn
Requires-Dist: scipy
